yang/__init__.py
yang/verification/__init__.py
yang/verification/bgp_network_schema.py
yang/verification/bgp_network_validate.py
yang/verification/common.py
yang/verification/common_types.py
yang/verification/portChannel_add_vlan_schema.py
yang/verification/portChannel_remove_vlan_schema.py
yang/verification/portChannel_schema.py
yang/verification/portChannel_validate.py
yang/verification/set_example.py
yang/verification/validate.py
yang/verification/vlan_config.py
yang/verification/vlan_ip_schema.py
yang/verification/vlan_schema.py
yang/verification/vlan_update_schema.py
yang/verification/vlan_validate.py
YangVerification-1.0.4.dist-info/LICENSE.txt
YangVerification-1.0.4.dist-info/METADATA
YangVerification-1.0.4.dist-info/WHEEL
YangVerification-1.0.4.dist-info/top_level.txt
YangVerification-1.0.4.dist-info/RECORD
