Metadata-Version: 2.1
Name: YangVerification
Version: 1.0.4
Summary: verification model for ali nertwork
Home-page: http://gitlab.alibaba-inc.com/xnet3/xnet3-yang
Author: Steven.yqb
Author-email: qiaobo.yqb@alibaba.com
License: UNKNOWN
Platform: UNKNOWN
